sdds/__init__.py
sdds/classes.py
sdds/reader.py
sdds/writer.py
sdds-0.4.3.dist-info/METADATA
sdds-0.4.3.dist-info/WHEEL
sdds-0.4.3.dist-info/licenses/LICENSE
sdds-0.4.3.dist-info/RECORD
