Metadata-Version: 2.4
Name: sdds
Version: 0.4.3
Summary: SDDS file handling.
Project-URL: homepage, https://github.com/pylhc/sdds
Project-URL: repository, https://github.com/pylhc/sdds
Project-URL: documentation, https://pylhc.github.io/sdds/
Project-URL: changelog, https://github.com/pylhc/sdds/blob/master/CHANGELOG.md
Author-email: OMC Team <pylhc@github.com>
License-Expression: MIT
License-File: LICENSE
Keywords: SDDS
Classifier: Development Status :: 5 - Production/Stable
Classifier: Intended Audience :: Science/Research
Classifier: License :: OSI Approved :: MIT License
Classifier: Natural Language :: English
Classifier: Operating System :: OS Independent
Classifier: Programming Language :: Python :: 3 :: Only
Classifier: Programming Language :: Python :: 3.10
Classifier: Programming Language :: Python :: 3.11
Classifier: Programming Language :: Python :: 3.12
Classifier: Programming Language :: Python :: 3.13
Classifier: Programming Language :: Python :: 3.14
Classifier: Programming Language :: Python :: Implementation :: CPython
Classifier: Topic :: Scientific/Engineering
Classifier: Topic :: Software Development :: Libraries :: Python Modules
Classifier: Typing :: Typed
Requires-Python: >=3.10
Requires-Dist: numpy>=1.24
Provides-Extra: all
Requires-Dist: pytest-cov>=2.9; extra == 'all'
Requires-Dist: pytest>=7.0; extra == 'all'
Requires-Dist: sphinx-rtd-theme>=2.0; extra == 'all'
Requires-Dist: sphinx>=7.0; extra == 'all'
Provides-Extra: doc
Requires-Dist: sphinx-rtd-theme>=2.0; extra == 'doc'
Requires-Dist: sphinx>=7.0; extra == 'doc'
Provides-Extra: test
Requires-Dist: pytest-cov>=2.9; extra == 'test'
Requires-Dist: pytest>=7.0; extra == 'test'
